pyfuture-0.0.14.dist-info/METADATA
pyfuture-0.0.14.dist-info/WHEEL
pyfuture-0.0.14.dist-info/entry_points.txt
pyfuture/__init__.py
pyfuture/__main__.py
pyfuture/__version__.py
pyfuture/codemod/__init__.py
pyfuture/codemod/pep604/__init__.py
pyfuture/codemod/pep604/union_types.py
pyfuture/codemod/pep622/__init__.py
pyfuture/codemod/pep622/match.py
pyfuture/codemod/pep695/__init__.py
pyfuture/codemod/pep695/type_parameters.py
pyfuture/codemod/pep701/__init__.py
pyfuture/codemod/pep701/fstring.py
pyfuture/codemod/utils.py
pyfuture/hooks/__init__.py
pyfuture/hooks/pdm.py
pyfuture/transformer/__init__.py
pyfuture/transformer/replace.py
pyfuture/utils.py
pyfuture-0.0.14.dist-info/RECORD
