Metadata-Version: 2.1
Name: pyfuture
Version: 0.0.14
Author-Email: Zhan Rongrui <2742392377@qq.com>
License: MIT
Project-URL: Homepage, https://github.com/zrr-lab/pyfuture.git
Project-URL: Repository, https://github.com/zrr-lab/pyfuture.git
Requires-Python: >=3.9
Requires-Dist: libcst>=1.2.0
Requires-Dist: typer>=0.9.0
Requires-Dist: loguru>=0.7.2
Requires-Dist: rich>=13.7.0
Requires-Dist: watchfiles; extra == "watch"
Requires-Dist: pyfuture[watch]; extra == "all"
Provides-Extra: watch
Provides-Extra: all
